{
  "WAGA Wellness": {
    "color": {
      "brand": {
        "olive": {
          "$value": "#5F6F52",
          "$type": "color",
          "$description": "Dark Olive Green \u2014 botanical accent, subtle"
        },
        "laurel": {
          "$value": "#A9B388",
          "$type": "color",
          "$description": "Laurel Green \u2014 botanical accent, light"
        },
        "cornsilk": {
          "$value": "#FEFAE0",
          "$type": "color",
          "$description": "Cornsilk \u2014 primary background, warm white"
        },
        "meringue": {
          "$value": "#F9EBC7",
          "$type": "color",
          "$description": "Lemon Meringue \u2014 secondary background, sand"
        },
        "camel": {
          "$value": "#B99470",
          "$type": "color",
          "$description": "Camel \u2014 primary brand anchor"
        },
        "alloy": {
          "$value": "#C4661F",
          "$type": "color",
          "$description": "Alloy Orange \u2014 accent, CTAs"
        },
        "russet": {
          "$value": "#783D19",
          "$type": "color",
          "$description": "Russet \u2014 accent, deep"
        }
      },
      "neutral": {
        "50": {
          "$value": "#FDFBF5",
          "$type": "color"
        },
        "100": {
          "$value": "#FAF6EC",
          "$type": "color"
        },
        "200": {
          "$value": "#F3ECDA",
          "$type": "color"
        },
        "300": {
          "$value": "#E5DBBF",
          "$type": "color"
        },
        "400": {
          "$value": "#C9B896",
          "$type": "color"
        },
        "500": {
          "$value": "#A6926E",
          "$type": "color"
        },
        "600": {
          "$value": "#8A7556",
          "$type": "color"
        },
        "700": {
          "$value": "#6B5A42",
          "$type": "color"
        },
        "800": {
          "$value": "#4A3D2E",
          "$type": "color"
        },
        "900": {
          "$value": "#2E2518",
          "$type": "color"
        },
        "950": {
          "$value": "#1A150D",
          "$type": "color"
        }
      },
      "primary": {
        "50": {
          "$value": "#FBF5EE",
          "$type": "color"
        },
        "100": {
          "$value": "#F5E8D5",
          "$type": "color"
        },
        "200": {
          "$value": "#EDCFAA",
          "$type": "color"
        },
        "300": {
          "$value": "#DFB07A",
          "$type": "color"
        },
        "400": {
          "$value": "#B99470",
          "$type": "color"
        },
        "500": {
          "$value": "#A67D56",
          "$type": "color"
        },
        "600": {
          "$value": "#8F6843",
          "$type": "color"
        },
        "700": {
          "$value": "#755436",
          "$type": "color"
        },
        "800": {
          "$value": "#5E432D",
          "$type": "color"
        },
        "900": {
          "$value": "#4A3525",
          "$type": "color"
        }
      },
      "accent": {
        "50": {
          "$value": "#FDF3EB",
          "$type": "color"
        },
        "100": {
          "$value": "#FAE0CA",
          "$type": "color"
        },
        "200": {
          "$value": "#F1C297",
          "$type": "color"
        },
        "300": {
          "$value": "#E49C5E",
          "$type": "color"
        },
        "400": {
          "$value": "#C4661F",
          "$type": "color"
        },
        "500": {
          "$value": "#A8571A",
          "$type": "color"
        },
        "600": {
          "$value": "#8D4917",
          "$type": "color"
        },
        "700": {
          "$value": "#783D19",
          "$type": "color"
        },
        "800": {
          "$value": "#5F3015",
          "$type": "color"
        },
        "900": {
          "$value": "#462311",
          "$type": "color"
        }
      },
      "botanical": {
        "50": {
          "$value": "#F4F6F0",
          "$type": "color"
        },
        "100": {
          "$value": "#E6EADE",
          "$type": "color"
        },
        "200": {
          "$value": "#CDD6BE",
          "$type": "color"
        },
        "300": {
          "$value": "#A9B388",
          "$type": "color"
        },
        "400": {
          "$value": "#8A9A6E",
          "$type": "color"
        },
        "500": {
          "$value": "#5F6F52",
          "$type": "color"
        },
        "600": {
          "$value": "#4D5B43",
          "$type": "color"
        },
        "700": {
          "$value": "#3D4836",
          "$type": "color"
        },
        "800": {
          "$value": "#2E362A",
          "$type": "color"
        },
        "900": {
          "$value": "#1F241D",
          "$type": "color"
        }
      },
      "success": {
        "50": {
          "$value": "#F2F5EC",
          "$type": "color"
        },
        "100": {
          "$value": "#E0E8D4",
          "$type": "color"
        },
        "200": {
          "$value": "#C5D4AE",
          "$type": "color"
        },
        "300": {
          "$value": "#9DB87E",
          "$type": "color"
        },
        "400": {
          "$value": "#7A9B5A",
          "$type": "color"
        },
        "500": {
          "$value": "#5F7D45",
          "$type": "color"
        },
        "600": {
          "$value": "#4C6638",
          "$type": "color"
        },
        "700": {
          "$value": "#3D512E",
          "$type": "color"
        },
        "800": {
          "$value": "#314027",
          "$type": "color"
        },
        "900": {
          "$value": "#23301C",
          "$type": "color"
        },
        "bg": {
          "$value": "{color.success.50}",
          "$type": "color"
        },
        "border": {
          "$value": "{color.success.200}",
          "$type": "color"
        },
        "text": {
          "$value": "{color.success.700}",
          "$type": "color"
        },
        "icon": {
          "$value": "{color.success.500}",
          "$type": "color"
        },
        "solid": {
          "$value": "{color.success.500}",
          "$type": "color"
        }
      },
      "warning": {
        "50": {
          "$value": "#FDF5E6",
          "$type": "color"
        },
        "100": {
          "$value": "#FAE6C2",
          "$type": "color"
        },
        "200": {
          "$value": "#F2CE8E",
          "$type": "color"
        },
        "300": {
          "$value": "#E4B05A",
          "$type": "color"
        },
        "400": {
          "$value": "#CF9432",
          "$type": "color"
        },
        "500": {
          "$value": "#AD7A24",
          "$type": "color"
        },
        "600": {
          "$value": "#8C621E",
          "$type": "color"
        },
        "700": {
          "$value": "#704E1A",
          "$type": "color"
        },
        "800": {
          "$value": "#5A3E16",
          "$type": "color"
        },
        "900": {
          "$value": "#422E12",
          "$type": "color"
        },
        "bg": {
          "$value": "{color.warning.50}",
          "$type": "color"
        },
        "border": {
          "$value": "{color.warning.200}",
          "$type": "color"
        },
        "text": {
          "$value": "{color.warning.700}",
          "$type": "color"
        },
        "icon": {
          "$value": "{color.warning.500}",
          "$type": "color"
        },
        "solid": {
          "$value": "{color.warning.500}",
          "$type": "color"
        }
      },
      "error": {
        "50": {
          "$value": "#FBF0EB",
          "$type": "color"
        },
        "100": {
          "$value": "#F5D8CC",
          "$type": "color"
        },
        "200": {
          "$value": "#EDBAAA",
          "$type": "color"
        },
        "300": {
          "$value": "#D9907A",
          "$type": "color"
        },
        "400": {
          "$value": "#C06B50",
          "$type": "color"
        },
        "500": {
          "$value": "#A3533B",
          "$type": "color"
        },
        "600": {
          "$value": "#864431",
          "$type": "color"
        },
        "700": {
          "$value": "#6B3728",
          "$type": "color"
        },
        "800": {
          "$value": "#552C21",
          "$type": "color"
        },
        "900": {
          "$value": "#3E201A",
          "$type": "color"
        },
        "bg": {
          "$value": "{color.error.50}",
          "$type": "color"
        },
        "border": {
          "$value": "{color.error.200}",
          "$type": "color"
        },
        "text": {
          "$value": "{color.error.700}",
          "$type": "color"
        },
        "icon": {
          "$value": "{color.error.500}",
          "$type": "color"
        },
        "solid": {
          "$value": "{color.error.500}",
          "$type": "color"
        }
      },
      "info": {
        "50": {
          "$value": "#F0F1F4",
          "$type": "color"
        },
        "100": {
          "$value": "#DCDEE5",
          "$type": "color"
        },
        "200": {
          "$value": "#B9BDCA",
          "$type": "color"
        },
        "300": {
          "$value": "#939AAD",
          "$type": "color"
        },
        "400": {
          "$value": "#6F7890",
          "$type": "color"
        },
        "500": {
          "$value": "#586177",
          "$type": "color"
        },
        "600": {
          "$value": "#474F62",
          "$type": "color"
        },
        "700": {
          "$value": "#3A3F4F",
          "$type": "color"
        },
        "800": {
          "$value": "#2E323F",
          "$type": "color"
        },
        "900": {
          "$value": "#22252E",
          "$type": "color"
        },
        "bg": {
          "$value": "{color.info.50}",
          "$type": "color"
        },
        "border": {
          "$value": "{color.info.200}",
          "$type": "color"
        },
        "text": {
          "$value": "{color.info.700}",
          "$type": "color"
        },
        "icon": {
          "$value": "{color.info.500}",
          "$type": "color"
        },
        "solid": {
          "$value": "{color.info.500}",
          "$type": "color"
        }
      },
      "bg": {
        "page": {
          "$value": "{color.neutral.50}",
          "$type": "color"
        },
        "cream": {
          "$value": "{color.brand.cornsilk}",
          "$type": "color"
        },
        "sand": {
          "$value": "{color.brand.meringue}",
          "$type": "color"
        },
        "card": {
          "$value": "#FFFFFF",
          "$type": "color"
        },
        "elevated": {
          "$value": "{color.neutral.100}",
          "$type": "color"
        },
        "muted": {
          "$value": "{color.neutral.200}",
          "$type": "color"
        },
        "inverse": {
          "$value": "{color.neutral.900}",
          "$type": "color"
        }
      },
      "text": {
        "primary": {
          "$value": "{color.neutral.900}",
          "$type": "color"
        },
        "secondary": {
          "$value": "{color.neutral.600}",
          "$type": "color"
        },
        "tertiary": {
          "$value": "{color.neutral.500}",
          "$type": "color"
        },
        "inverse": {
          "$value": "{color.neutral.50}",
          "$type": "color"
        },
        "accent": {
          "$value": "{color.accent.400}",
          "$type": "color"
        },
        "heading": {
          "$value": "{color.neutral.950}",
          "$type": "color"
        }
      },
      "border": {
        "default": {
          "$value": "rgba(107, 90, 66, 0.12)",
          "$type": "color"
        },
        "strong": {
          "$value": "rgba(107, 90, 66, 0.22)",
          "$type": "color"
        },
        "muted": {
          "$value": "rgba(107, 90, 66, 0.06)",
          "$type": "color"
        },
        "accent": {
          "$value": "{color.primary.400}",
          "$type": "color"
        }
      },
      "button": {
        "primary": {
          "bg": {
            "$value": "{color.accent.400}",
            "$type": "color"
          },
          "bgHover": {
            "$value": "{color.accent.500}",
            "$type": "color"
          },
          "text": {
            "$value": "#FFFFFF",
            "$type": "color"
          }
        },
        "secondary": {
          "bg": {
            "$value": "transparent",
            "$type": "color"
          },
          "border": {
            "$value": "{color.neutral.800}",
            "$type": "color"
          },
          "text": {
            "$value": "{color.neutral.800}",
            "$type": "color"
          }
        },
        "botanical": {
          "bg": {
            "$value": "{color.botanical.500}",
            "$type": "color"
          },
          "bgHover": {
            "$value": "{color.botanical.600}",
            "$type": "color"
          },
          "text": {
            "$value": "{color.brand.cornsilk}",
            "$type": "color"
          }
        }
      }
    },
    "fontFamily": {
      "heading": {
        "$value": "Geist, 'Helvetica Neue', system-ui, sans-serif",
        "$type": "fontFamily"
      },
      "accent": {
        "$value": "Instrument Serif, Georgia, serif",
        "$type": "fontFamily",
        "$description": "Italic only \u2014 NEVER upright"
      },
      "body": {
        "$value": "Geist, 'Helvetica Neue', system-ui, sans-serif",
        "$type": "fontFamily"
      }
    },
    "fontWeight": {
      "regular": {
        "$value": "400",
        "$type": "fontWeight"
      },
      "medium": {
        "$value": "500",
        "$type": "fontWeight"
      },
      "semibold": {
        "$value": "600",
        "$type": "fontWeight"
      },
      "bold": {
        "$value": "700",
        "$type": "fontWeight"
      }
    },
    "fontSize": {
      "caption": {
        "$value": "12",
        "$type": "fontSizes"
      },
      "sm": {
        "$value": "14",
        "$type": "fontSizes"
      },
      "base": {
        "$value": "16",
        "$type": "fontSizes"
      },
      "lg": {
        "$value": "20",
        "$type": "fontSizes"
      },
      "xl": {
        "$value": "25",
        "$type": "fontSizes"
      },
      "2xl": {
        "$value": "31",
        "$type": "fontSizes"
      },
      "3xl": {
        "$value": "39",
        "$type": "fontSizes"
      },
      "4xl": {
        "$value": "49",
        "$type": "fontSizes"
      },
      "5xl": {
        "$value": "61",
        "$type": "fontSizes"
      },
      "6xl": {
        "$value": "76",
        "$type": "fontSizes"
      }
    },
    "lineHeight": {
      "caption": {
        "$value": "16",
        "$type": "lineHeights"
      },
      "sm": {
        "$value": "20",
        "$type": "lineHeights"
      },
      "base": {
        "$value": "24",
        "$type": "lineHeights"
      },
      "lg": {
        "$value": "28",
        "$type": "lineHeights"
      },
      "xl": {
        "$value": "32",
        "$type": "lineHeights"
      },
      "2xl": {
        "$value": "40",
        "$type": "lineHeights"
      },
      "3xl": {
        "$value": "48",
        "$type": "lineHeights"
      },
      "4xl": {
        "$value": "56",
        "$type": "lineHeights"
      },
      "5xl": {
        "$value": "68",
        "$type": "lineHeights"
      },
      "6xl": {
        "$value": "84",
        "$type": "lineHeights"
      }
    },
    "letterSpacing": {
      "tighter": {
        "$value": "-2.5%",
        "$type": "letterSpacing",
        "$description": "Display headings (49px+) \u2014 Geist is naturally tight"
      },
      "tight": {
        "$value": "-1.5%",
        "$type": "letterSpacing",
        "$description": "Large headings (31-48px)"
      },
      "snug": {
        "$value": "-1%",
        "$type": "letterSpacing",
        "$description": "Medium headings (20-31px)"
      },
      "normal": {
        "$value": "0%",
        "$type": "letterSpacing"
      },
      "wide": {
        "$value": "2%",
        "$type": "letterSpacing",
        "$description": "Small text"
      },
      "wider": {
        "$value": "6%",
        "$type": "letterSpacing",
        "$description": "ALL CAPS labels"
      },
      "widest": {
        "$value": "10%",
        "$type": "letterSpacing",
        "$description": "Badges, spaced caps"
      }
    },
    "typography": {
      "display": {
        "$value": {
          "fontFamily": "{fontFamily.heading}",
          "fontWeight": "{fontWeight.regular}",
          "fontSize": "{fontSize.6xl}",
          "lineHeight": "{lineHeight.6xl}",
          "letterSpacing": "{letterSpacing.tighter}"
        },
        "$type": "typography",
        "$description": "76px \u2014 hero headlines"
      },
      "h1": {
        "$value": {
          "fontFamily": "{fontFamily.heading}",
          "fontWeight": "{fontWeight.regular}",
          "fontSize": "{fontSize.5xl}",
          "lineHeight": "{lineHeight.5xl}",
          "letterSpacing": "{letterSpacing.tighter}"
        },
        "$type": "typography"
      },
      "h2": {
        "$value": {
          "fontFamily": "{fontFamily.heading}",
          "fontWeight": "{fontWeight.regular}",
          "fontSize": "{fontSize.4xl}",
          "lineHeight": "{lineHeight.4xl}",
          "letterSpacing": "{letterSpacing.tight}"
        },
        "$type": "typography"
      },
      "h3": {
        "$value": {
          "fontFamily": "{fontFamily.heading}",
          "fontWeight": "{fontWeight.regular}",
          "fontSize": "{fontSize.3xl}",
          "lineHeight": "{lineHeight.3xl}",
          "letterSpacing": "{letterSpacing.tight}"
        },
        "$type": "typography"
      },
      "h4": {
        "$value": {
          "fontFamily": "{fontFamily.heading}",
          "fontWeight": "{fontWeight.regular}",
          "fontSize": "{fontSize.2xl}",
          "lineHeight": "{lineHeight.2xl}",
          "letterSpacing": "{letterSpacing.snug}"
        },
        "$type": "typography"
      },
      "h5": {
        "$value": {
          "fontFamily": "{fontFamily.heading}",
          "fontWeight": "{fontWeight.regular}",
          "fontSize": "{fontSize.xl}",
          "lineHeight": "{lineHeight.xl}",
          "letterSpacing": "{letterSpacing.snug}"
        },
        "$type": "typography"
      },
      "accentDisplay": {
        "$value": {
          "fontFamily": "{fontFamily.accent}",
          "fontWeight": "{fontWeight.regular}",
          "fontSize": "{fontSize.6xl}",
          "lineHeight": "{lineHeight.6xl}",
          "letterSpacing": "{letterSpacing.tighter}"
        },
        "$type": "typography",
        "$description": "Instrument Serif Italic \u2014 use italic style in Figma"
      },
      "accentLarge": {
        "$value": {
          "fontFamily": "{fontFamily.accent}",
          "fontWeight": "{fontWeight.regular}",
          "fontSize": "{fontSize.4xl}",
          "lineHeight": "{lineHeight.4xl}",
          "letterSpacing": "{letterSpacing.tight}"
        },
        "$type": "typography",
        "$description": "Instrument Serif Italic \u2014 use italic style in Figma"
      },
      "accentMedium": {
        "$value": {
          "fontFamily": "{fontFamily.accent}",
          "fontWeight": "{fontWeight.regular}",
          "fontSize": "{fontSize.2xl}",
          "lineHeight": "{lineHeight.2xl}",
          "letterSpacing": "{letterSpacing.snug}"
        },
        "$type": "typography",
        "$description": "Instrument Serif Italic \u2014 use italic style in Figma"
      },
      "accentSmall": {
        "$value": {
          "fontFamily": "{fontFamily.accent}",
          "fontWeight": "{fontWeight.regular}",
          "fontSize": "{fontSize.lg}",
          "lineHeight": "{lineHeight.lg}",
          "letterSpacing": "{letterSpacing.normal}"
        },
        "$type": "typography",
        "$description": "Instrument Serif Italic \u2014 use italic style in Figma"
      },
      "bodyLarge": {
        "$value": {
          "fontFamily": "{fontFamily.body}",
          "fontWeight": "{fontWeight.regular}",
          "fontSize": "{fontSize.lg}",
          "lineHeight": "{lineHeight.xl}",
          "letterSpacing": "{letterSpacing.normal}"
        },
        "$type": "typography"
      },
      "body": {
        "$value": {
          "fontFamily": "{fontFamily.body}",
          "fontWeight": "{fontWeight.regular}",
          "fontSize": "{fontSize.base}",
          "lineHeight": "{lineHeight.base}",
          "letterSpacing": "{letterSpacing.normal}"
        },
        "$type": "typography"
      },
      "small": {
        "$value": {
          "fontFamily": "{fontFamily.body}",
          "fontWeight": "{fontWeight.regular}",
          "fontSize": "{fontSize.sm}",
          "lineHeight": "{lineHeight.sm}",
          "letterSpacing": "{letterSpacing.normal}"
        },
        "$type": "typography"
      },
      "caption": {
        "$value": {
          "fontFamily": "{fontFamily.body}",
          "fontWeight": "{fontWeight.regular}",
          "fontSize": "{fontSize.caption}",
          "lineHeight": "{lineHeight.caption}",
          "letterSpacing": "{letterSpacing.wider}"
        },
        "$type": "typography",
        "$description": "Uppercase labels and captions"
      }
    },
    "spacing": {
      "3xs": {
        "$value": "2",
        "$type": "spacing"
      },
      "2xs": {
        "$value": "4",
        "$type": "spacing"
      },
      "xs": {
        "$value": "8",
        "$type": "spacing"
      },
      "sm": {
        "$value": "12",
        "$type": "spacing"
      },
      "md": {
        "$value": "16",
        "$type": "spacing"
      },
      "lg": {
        "$value": "24",
        "$type": "spacing"
      },
      "xl": {
        "$value": "32",
        "$type": "spacing"
      },
      "2xl": {
        "$value": "48",
        "$type": "spacing"
      },
      "3xl": {
        "$value": "64",
        "$type": "spacing"
      },
      "4xl": {
        "$value": "96",
        "$type": "spacing"
      },
      "5xl": {
        "$value": "128",
        "$type": "spacing"
      },
      "6xl": {
        "$value": "192",
        "$type": "spacing"
      }
    },
    "borderRadius": {
      "none": {
        "$value": "0",
        "$type": "borderRadius"
      },
      "sm": {
        "$value": "4",
        "$type": "borderRadius"
      },
      "md": {
        "$value": "8",
        "$type": "borderRadius"
      },
      "lg": {
        "$value": "12",
        "$type": "borderRadius"
      },
      "xl": {
        "$value": "16",
        "$type": "borderRadius"
      },
      "2xl": {
        "$value": "24",
        "$type": "borderRadius"
      },
      "full": {
        "$value": "9999",
        "$type": "borderRadius"
      }
    },
    "boxShadow": {
      "xs": {
        "$value": [
          {
            "x": 0,
            "y": 1,
            "blur": 2,
            "spread": 0,
            "color": "rgba(74, 61, 46, 0.06)",
            "type": "dropShadow"
          }
        ],
        "$type": "boxShadow"
      },
      "sm": {
        "$value": [
          {
            "x": 0,
            "y": 1,
            "blur": 3,
            "spread": 0,
            "color": "rgba(74, 61, 46, 0.08)",
            "type": "dropShadow"
          },
          {
            "x": 0,
            "y": 1,
            "blur": 2,
            "spread": 0,
            "color": "rgba(74, 61, 46, 0.04)",
            "type": "dropShadow"
          }
        ],
        "$type": "boxShadow"
      },
      "md": {
        "$value": [
          {
            "x": 0,
            "y": 4,
            "blur": 8,
            "spread": 0,
            "color": "rgba(74, 61, 46, 0.08)",
            "type": "dropShadow"
          },
          {
            "x": 0,
            "y": 2,
            "blur": 4,
            "spread": 0,
            "color": "rgba(74, 61, 46, 0.04)",
            "type": "dropShadow"
          }
        ],
        "$type": "boxShadow"
      },
      "lg": {
        "$value": [
          {
            "x": 0,
            "y": 12,
            "blur": 24,
            "spread": 0,
            "color": "rgba(74, 61, 46, 0.10)",
            "type": "dropShadow"
          },
          {
            "x": 0,
            "y": 4,
            "blur": 8,
            "spread": 0,
            "color": "rgba(74, 61, 46, 0.04)",
            "type": "dropShadow"
          }
        ],
        "$type": "boxShadow"
      },
      "xl": {
        "$value": [
          {
            "x": 0,
            "y": 20,
            "blur": 40,
            "spread": 0,
            "color": "rgba(74, 61, 46, 0.12)",
            "type": "dropShadow"
          },
          {
            "x": 0,
            "y": 8,
            "blur": 16,
            "spread": 0,
            "color": "rgba(74, 61, 46, 0.04)",
            "type": "dropShadow"
          }
        ],
        "$type": "boxShadow"
      },
      "2xl": {
        "$value": [
          {
            "x": 0,
            "y": 32,
            "blur": 64,
            "spread": 0,
            "color": "rgba(74, 61, 46, 0.16)",
            "type": "dropShadow"
          }
        ],
        "$type": "boxShadow"
      }
    },
    "sizing": {
      "button": {
        "sm": {
          "$value": "36",
          "$type": "sizing"
        },
        "md": {
          "$value": "44",
          "$type": "sizing"
        },
        "lg": {
          "$value": "52",
          "$type": "sizing"
        }
      },
      "input": {
        "sm": {
          "$value": "36",
          "$type": "sizing"
        },
        "md": {
          "$value": "44",
          "$type": "sizing"
        },
        "lg": {
          "$value": "52",
          "$type": "sizing"
        }
      },
      "nav": {
        "desktop": {
          "$value": "64",
          "$type": "sizing"
        },
        "mobile": {
          "$value": "56",
          "$type": "sizing"
        }
      },
      "container": {
        "sm": {
          "$value": "640",
          "$type": "sizing"
        },
        "md": {
          "$value": "768",
          "$type": "sizing"
        },
        "lg": {
          "$value": "1024",
          "$type": "sizing"
        },
        "xl": {
          "$value": "1280",
          "$type": "sizing"
        },
        "2xl": {
          "$value": "1440",
          "$type": "sizing"
        }
      }
    },
    "opacity": {
      "0": {
        "$value": "0%",
        "$type": "opacity"
      },
      "5": {
        "$value": "5%",
        "$type": "opacity"
      },
      "10": {
        "$value": "10%",
        "$type": "opacity"
      },
      "20": {
        "$value": "20%",
        "$type": "opacity"
      },
      "40": {
        "$value": "40%",
        "$type": "opacity"
      },
      "60": {
        "$value": "60%",
        "$type": "opacity"
      },
      "80": {
        "$value": "80%",
        "$type": "opacity"
      },
      "100": {
        "$value": "100%",
        "$type": "opacity"
      }
    },
    "component": {
      "button": {
        "radius": {
          "$value": "{borderRadius.md}",
          "$type": "borderRadius",
          "$description": "8px \u2014 warm, approachable"
        },
        "weight": {
          "$value": "{fontWeight.medium}",
          "$type": "fontWeight"
        },
        "tracking": {
          "$value": "{letterSpacing.wide}",
          "$type": "letterSpacing"
        }
      },
      "input": {
        "radius": {
          "$value": "{borderRadius.md}",
          "$type": "borderRadius",
          "$description": "Match buttons"
        }
      },
      "badge": {
        "radius": {
          "$value": "{borderRadius.full}",
          "$type": "borderRadius"
        },
        "fontSize": {
          "$value": "11",
          "$type": "fontSize"
        },
        "weight": {
          "$value": "{fontWeight.bold}",
          "$type": "fontWeight"
        },
        "tracking": {
          "$value": "{letterSpacing.widest}",
          "$type": "letterSpacing"
        },
        "accent": {
          "bg": {
            "$value": "rgba(196, 102, 31, 0.06)",
            "$type": "color"
          },
          "text": {
            "$value": "{color.accent.400}",
            "$type": "color"
          },
          "border": {
            "$value": "rgba(196, 102, 31, 0.20)",
            "$type": "color"
          }
        },
        "warm": {
          "bg": {
            "$value": "{color.primary.50}",
            "$type": "color"
          },
          "text": {
            "$value": "{color.primary.600}",
            "$type": "color"
          },
          "border": {
            "$value": "{color.primary.200}",
            "$type": "color"
          }
        },
        "sand": {
          "bg": {
            "$value": "{color.neutral.100}",
            "$type": "color"
          },
          "text": {
            "$value": "{color.neutral.600}",
            "$type": "color"
          },
          "border": {
            "$value": "{color.neutral.300}",
            "$type": "color"
          }
        },
        "botanical": {
          "bg": {
            "$value": "rgba(169, 179, 136, 0.10)",
            "$type": "color"
          },
          "text": {
            "$value": "{color.botanical.500}",
            "$type": "color"
          },
          "border": {
            "$value": "{color.botanical.100}",
            "$type": "color"
          }
        }
      }
    }
  }
}